stashhouse_ssh/__init__.py
stashhouse_ssh/connection.py
stashhouse_ssh/sftp.py
stashhouse_ssh/stream.py
stashhouse_ssh-0.0.5.dist-info/METADATA
stashhouse_ssh-0.0.5.dist-info/WHEEL
stashhouse_ssh-0.0.5.dist-info/entry_points.txt
stashhouse_ssh-0.0.5.dist-info/licenses/LICENSE
stashhouse_ssh-0.0.5.dist-info/RECORD
