Metadata-Version: 2.4
Name: stashhouse_ssh
Version: 0.0.5
Summary: StashHouse plugin for SCP and SFTP
Project-URL: Homepage, https://github.com/Jayson-Fong/stashhouse-ssh
Project-URL: Issues, https://github.com/Jayson-Fong/stashhouse-ssh/issues
Author-email: Jayson Fong <jayson.fong@gatech.edu>
License: MIT AND (EPL-2.0 OR GPL-2.0-or-later)
License-File: LICENSE
Classifier: Development Status :: 1 - Planning
Classifier: License :: OSI Approved :: Eclipse Public License 2.0 (EPL-2.0)
Classifier: License :: OSI Approved :: GNU General Public License v2 or later (GPLv2+)
Classifier: License :: OSI Approved :: MIT License
Classifier: Operating System :: OS Independent
Classifier: Programming Language :: Python
Classifier: Programming Language :: Python :: 3.11
Classifier: Programming Language :: Python :: 3.12
Classifier: Programming Language :: Python :: 3.13
Requires-Python: >=3.11
Requires-Dist: asyncssh==2.21.0
Requires-Dist: stashhouse>=0.0.4
